mola/__init__.py
mola/clustering.py
mola/decomposition.py
mola/matrix.py
mola/regression.py
mola/utils.py
mola-2.0.0.dist-info/LICENSE
mola-2.0.0.dist-info/METADATA
mola-2.0.0.dist-info/WHEEL
mola-2.0.0.dist-info/top_level.txt
mola-2.0.0.dist-info/RECORD
