Metadata-Version: 2.1
Name: mola
Version: 2.0.0
Summary: Matrix operations and linear algebra (mola) library without external dependencies
Home-page: https://github.com/jerela/mola
Author: Jere Lavikainen
Author-email: lavikainen.jere@gmail.com
License: MIT
Classifier: Intended Audience :: Developers
Classifier: License :: OSI Approved :: MIT License
Classifier: Programming Language :: Python
Classifier: Programming Language :: Python :: 3
Classifier: Programming Language :: Python :: 3.6
Classifier: Programming Language :: Python :: 3.7
Classifier: Programming Language :: Python :: 3.8
Classifier: Programming Language :: Python :: 3.9
Classifier: Operating System :: OS Independent
License-File: LICENSE
